setup.py
common/__init__.py
common/answers.py
common/decorators.py
common/descryptors.py
common/errors.py
common/metaclasses.py
common/utils.py
log/__init__.py
log/client_log_config.py
log/server_log_config.py
samoryad_messenger_server.egg-info/PKG-INFO
samoryad_messenger_server.egg-info/SOURCES.txt
samoryad_messenger_server.egg-info/dependency_links.txt
samoryad_messenger_server.egg-info/requires.txt
samoryad_messenger_server.egg-info/top_level.txt
server/__init__.py
server/add_user.py
server/config_window.py
server/core.py
server/database.py
server/main_window.py
server/remove_user.py
server/stat_window.py