Metadata-Version: 1.0
Name: samoryad-messenger-server
Version: 0.0.2
Summary: mess_server
Home-page: UNKNOWN
Author: Andrey Samoryadov
Author-email: samoryadov@yandex.ru
License: UNKNOWN
Platform: UNKNOWN
